py_encase/__init__.py
py_encase/py_encase.py
py_encase-0.0.24.dist-info/licenses/LICENSE
share/py-encase/template/.gitkeep
share/py-encase/template/py_encase_template.py
py_encase-0.0.24.dist-info/METADATA
py_encase-0.0.24.dist-info/WHEEL
py_encase-0.0.24.dist-info/entry_points.txt
py_encase-0.0.24.dist-info/top_level.txt
py_encase-0.0.24.dist-info/RECORD
