Metadata-Version: 2.4
Name: py-encase
Version: 0.0.24
Summary: Tool for encased python script environment.
Author-email: Nanigashi Uji <53845049+nanigashi-uji@users.noreply.github.com>, Nanigashi Uji <4423013-nanigashi_uji@users.noreply.gitlab.com>
Maintainer-email: Nanigashi Uji <53845049+nanigashi-uji@users.noreply.github.com>, Nanigashi Uji <4423013-nanigashi_uji@users.noreply.gitlab.com>
License: BSD 3-Clause License
Project-URL: Homepage, https://github.com/nanigashi-uji/py-encase
Keywords: pip,template,development
Classifier: Development Status :: 2 - Pre-Alpha
Classifier: Programming Language :: Python
Classifier: Programming Language :: Python :: 3
Classifier: Programming Language :: Python :: 3.9
Classifier: Programming Language :: Python :: 3.10
Classifier: Programming Language :: Python :: 3.11
Classifier: Programming Language :: Python :: 3.12
Classifier: Programming Language :: Python :: 3.13
Classifier: Topic :: Software Development
Classifier: Topic :: Utilities
Requires-Python: >=3.9
License-File: LICENSE
Dynamic: license-file
